camera_input_live/__init__.py
camera_input_live/frontend/index.html
camera_input_live/frontend/main.js
camera_input_live/frontend/streamlit-component-lib.js
camera_input_live/frontend/style.css
streamlit_camera_input_live-0.2.0.dist-info/LICENSE
streamlit_camera_input_live-0.2.0.dist-info/METADATA
streamlit_camera_input_live-0.2.0.dist-info/WHEEL
streamlit_camera_input_live-0.2.0.dist-info/top_level.txt
streamlit_camera_input_live-0.2.0.dist-info/RECORD
