Metadata-Version: 2.1
Name: streamlit-camera-input-live
Version: 0.2.0
Summary: Alternative version of st.camera_input which returns the webcam images live, without any button press needed
Home-page: https://github.com/blackary/streamlit-camera-input-live
Author: Zachary Blackwood
Author-email: zachary@streamlit.io
Requires-Python: >=3.7
License-File: LICENSE
